setup.py
Erik.egg-info/PKG-INFO
Erik.egg-info/SOURCES.txt
Erik.egg-info/dependency_links.txt
Erik.egg-info/top_level.txt
erik/__init__.py
erik/utils/__init__.py
erik/utils/misc.py