Metadata-Version: 1.0
Name: Erik
Version: 0.0.1
Summary: Erik Misc
Home-page: UNKNOWN
Author: Erik Gafni
Author-email: UNKNOWN
License: Non-commercial
Platform: UNKNOWN
